yoinkr/__init__.py
yoinkr/py.typed
yoinkr/core/__init__.py
yoinkr/core/browser_config.py
yoinkr/core/circuit_breaker.py
yoinkr/core/config.py
yoinkr/core/exceptions.py
yoinkr/core/extractor.py
yoinkr/core/fetcher.py
yoinkr/core/health.py
yoinkr/core/rate_limiter.py
yoinkr/core/scraper.py
yoinkr/core/security.py
yoinkr/core/types.py
yoinkr/core/validation.py
yoinkr/core/methods/__init__.py
yoinkr/core/methods/attr.py
yoinkr/core/methods/base.py
yoinkr/core/methods/css.py
yoinkr/core/methods/jsonpath.py
yoinkr/core/methods/meta.py
yoinkr/core/methods/regex.py
yoinkr/core/methods/text.py
yoinkr/core/methods/xpath.py
yoinkr/django/__init__.py
yoinkr/django/admin.py
yoinkr/django/apps.py
yoinkr/django/models.py
yoinkr/django/tasks.py
yoinkr/django/management/__init__.py
yoinkr/django/management/commands/__init__.py
yoinkr/django/management/commands/scrape.py
yoinkr/django/migrations/0001_initial.py
yoinkr/django/migrations/__init__.py
yoinkr/utils/__init__.py
yoinkr/utils/input.py
yoinkr/utils/logging.py
yoinkr/utils/page.py
yoinkr/utils/proxy.py
yoinkr/utils/retry.py
yoinkr/utils/statistics.py
yoinkr/utils/user_agents.py
yoinkr-0.2.0.dist-info/METADATA
yoinkr-0.2.0.dist-info/WHEEL
yoinkr-0.2.0.dist-info/entry_points.txt
yoinkr-0.2.0.dist-info/RECORD
