Metadata-Version: 2.4
Name: yoinkr
Version: 0.2.0
Summary: Yoink data from any website - a powerful web scraping library for Python and Django
Project-URL: Homepage, https://github.com/yoinkr/yoinkr
Project-URL: Documentation, https://github.com/yoinkr/yoinkr#readme
Project-URL: Repository, https://github.com/yoinkr/yoinkr
Project-URL: Issues, https://github.com/yoinkr/yoinkr/issues
Author: Yoinkr Contributors
License-Expression: MIT
Keywords: async,beautifulsoup,data-extraction,django,playwright,scraper,web-scraping,yoinkr
Classifier: Development Status :: 4 - Beta
Classifier: Framework :: Django
Classifier: Framework :: Django :: 4.2
Classifier: Framework :: Django :: 5.0
Classifier: Intended Audience :: Developers
Classifier: License :: OSI Approved :: MIT License
Classifier: Operating System :: OS Independent
Classifier: Programming Language :: Python :: 3
Classifier: Programming Language :: Python :: 3.10
Classifier: Programming Language :: Python :: 3.11
Classifier: Programming Language :: Python :: 3.12
Classifier: Topic :: Internet :: WWW/HTTP
Classifier: Topic :: Software Development :: Libraries :: Python Modules
Classifier: Typing :: Typed
Requires-Python: >=3.10
Requires-Dist: beautifulsoup4>=4.12.0
Requires-Dist: httpx>=0.25.0
Requires-Dist: lxml>=5.0.0
Requires-Dist: playwright>=1.40.0
Provides-Extra: all
Requires-Dist: celery>=5.3.0; extra == 'all'
Requires-Dist: django>=4.2; extra == 'all'
Provides-Extra: celery
Requires-Dist: celery>=5.3.0; extra == 'celery'
Provides-Extra: dev
Requires-Dist: mypy>=1.0; extra == 'dev'
Requires-Dist: pytest-asyncio>=0.21.0; extra == 'dev'
Requires-Dist: pytest-cov>=4.0; extra == 'dev'
Requires-Dist: pytest>=7.0; extra == 'dev'
Requires-Dist: ruff>=0.1.0; extra == 'dev'
Provides-Extra: django
Requires-Dist: django>=4.2; extra == 'django'
